setup.py
webportfolio_rq_worker.py
webportfolio_rq_worker.egg-info/PKG-INFO
webportfolio_rq_worker.egg-info/SOURCES.txt
webportfolio_rq_worker.egg-info/dependency_links.txt
webportfolio_rq_worker.egg-info/pbr.json
webportfolio_rq_worker.egg-info/requires.txt
webportfolio_rq_worker.egg-info/top_level.txt